mycompat/__init__.py
mycompat/__init__.pyi
mycompat-0.1.1.dist-info/LICENSE
mycompat-0.1.1.dist-info/METADATA
mycompat-0.1.1.dist-info/WHEEL
mycompat-0.1.1.dist-info/top_level.txt
mycompat-0.1.1.dist-info/RECORD
