Metadata-Version: 2.1
Name: mycompat
Version: 0.1.1
Summary: A lightweight compatibility library designed to facilitate the retrieval of system version information and various other system details
Author-email: Isaiah Coroama <coroamaisaiah@gmail.com>
License: GNU GENERAL PUBLIC LICENSE
Project-URL: Homepage, https://github.com/IsaiahCoroama/mycompat
Keywords: compatibility,library,lightweight,system
Classifier: Intended Audience :: Developers
Requires-Python: >=3.3
License-File: LICENSE
